pycodereview/__init__.py
pycodereview/__main__.py
pycodereview/code_review.py
pycodereview-2.0.0.dist-info/licenses/LICENSE
pycodereview-2.0.0.dist-info/licenses/LICENSE-CRSS
pycodereview-2.0.0.dist-info/METADATA
pycodereview-2.0.0.dist-info/WHEEL
pycodereview-2.0.0.dist-info/entry_points.txt
pycodereview-2.0.0.dist-info/top_level.txt
pycodereview-2.0.0.dist-info/RECORD
