Metadata-Version: 2.4
Name: pycodereview
Version: 2.0.0
Summary: Static checks for common Python code risks and hygiene issues.
Author-email: Sofian Daghsen <sofianjava@gmail.com>
License: MIT
Project-URL: Homepage, https://github.com/sofiand-png/pycodereview
Project-URL: Repository, https://github.com/sofiand-png/pycodereview
Project-URL: Issues, https://github.com/sofiand-png/pycodereview/issues
Project-URL: Changelog, https://github.com/sofiand-png/pycodereview/blob/main/CHANGELOG.md
Keywords: static analysis,code review,lint
Classifier: Development Status :: 5 - Production/Stable
Classifier: Intended Audience :: Developers
Classifier: License :: OSI Approved :: MIT License
Classifier: Programming Language :: Python :: 3
Classifier: Programming Language :: Python :: 3 :: Only
Classifier: Programming Language :: Python :: 3.9
Classifier: Programming Language :: Python :: 3.10
Classifier: Programming Language :: Python :: 3.11
Classifier: Programming Language :: Python :: 3.12
Classifier: Operating System :: OS Independent
Requires-Python: >=3.9
License-File: LICENSE
License-File: LICENSE-CRSS
Dynamic: license-file
